<?xml version="1.0" encoding="UTF-8"?>
<!DOCTYPE mytetradoc>
<root>
 <format version="1" subversion="2"/>
 <content>
  <node crypt="0" icon="" id="1542219045xznge0wft0" name="Техническая документация">
   <node crypt="0" icon="" id="1542219107whkk93rgnu" name="Android">
    <node crypt="" id="1542260746wrklgoddqf" name="Linux">
     <node crypt="" id="1542260760tir1nhbpuj" name="Проблемы и решения">
      <recordtable>
       <record id="1542260914i2a99jhj4h" name="Не загружается из за случайных чисел" author="" url="http://liberatum.ru/e/dev-random-urandom-haveged" tags="Linux, энтропия, загрузка, проблема" ctime="20181115084834" dir="154226091447jbo6tzw3" file="text.html"/>
      </recordtable>
     </node>
    </node>
   </node>
   <node crypt="0" icon="" id="1542219138spg8cgcbz6" name="Lego Robots">
    <recordtable>
     <record id="15422193147bp4leuri0" name="Прохождение лабиринта" author="" url="http://nxt33.blogspot.com/2013/04/blog-post_5912.html" tags="Lego, роботы" ctime="20181114211514" dir="15422193149c4p8qkjk6" file="text.html"/>
    </recordtable>
   </node>
   <node crypt="" id="1542220017agbxk14c3z" name="Сети">
    <node crypt="" id="1542220025d6vjz0jfu6" name="Mikrotik">
     <recordtable>
      <record id="1542220328vzo2s5flp7" name="Микротик в роли тестера" author="" url="https://habr.com/post/364593/" tags="mikrotik, тестер, diy" ctime="20181114213208" dir="15422203283686qe6ltm" file="text.html"/>
     </recordtable>
    </node>
    <node crypt="" id="1542220049cbnnakcpkh" name="Unifi"/>
   </node>
  </node>
 </content>
</root>
